lamar/__init__.py
lamar/cli.py
lamar/SynthSeg/__init__.py
lamar/SynthSeg/brain_generator.py
lamar/SynthSeg/estimate_priors.py
lamar/SynthSeg/evaluate.py
lamar/SynthSeg/labels_to_image_model.py
lamar/SynthSeg/metrics_model.py
lamar/SynthSeg/model_handler.py
lamar/SynthSeg/model_inputs.py
lamar/SynthSeg/predict.py
lamar/SynthSeg/predict_denoiser.py
lamar/SynthSeg/predict_group.py
lamar/SynthSeg/predict_qc.py
lamar/SynthSeg/predict_synthseg.py
lamar/SynthSeg/sample_segmentation_pairs_d.py
lamar/SynthSeg/training.py
lamar/SynthSeg/training_denoiser.py
lamar/SynthSeg/training_group.py
lamar/SynthSeg/training_qc.py
lamar/SynthSeg/training_supervised.py
lamar/SynthSeg/validate.py
lamar/SynthSeg/validate_denoiser.py
lamar/SynthSeg/validate_group.py
lamar/SynthSeg/validate_qc.py
lamar/ext/__init__.py
lamar/ext/lab2im/__init__.py
lamar/ext/lab2im/edit_tensors.py
lamar/ext/lab2im/edit_volumes.py
lamar/ext/lab2im/image_generator.py
lamar/ext/lab2im/lab2im_model.py
lamar/ext/lab2im/layers.py
lamar/ext/lab2im/utils.py
lamar/ext/neuron/__init__.py
lamar/ext/neuron/layers.py
lamar/ext/neuron/models.py
lamar/ext/neuron/utils.py
lamar/scripts/__init__.py
lamar/scripts/apply_warp.py
lamar/scripts/coregister.py
lamar/scripts/dice_compare.py
lamar/scripts/lamar.py
lamar/scripts/synthseg.py
lamar/scripts/data/labels_classes_priors/generation_classes.npy
lamar/scripts/data/labels_classes_priors/generation_classes_contrast_specific.npy
lamar/scripts/data/labels_classes_priors/generation_labels.npy
lamar/scripts/data/labels_classes_priors/prior_means_t1.npy
lamar/scripts/data/labels_classes_priors/prior_stds_t1.npy
lamar/scripts/data/labels_classes_priors/synthseg_denoiser_labels_2.0.npy
lamar/scripts/data/labels_classes_priors/synthseg_parcellation_labels.npy
lamar/scripts/data/labels_classes_priors/synthseg_parcellation_names.npy
lamar/scripts/data/labels_classes_priors/synthseg_qc_labels.npy
lamar/scripts/data/labels_classes_priors/synthseg_qc_labels_2.0.npy
lamar-1.0.4.dist-info/licenses/LICENSE
lamar-1.0.4.dist-info/METADATA
lamar-1.0.4.dist-info/WHEEL
lamar-1.0.4.dist-info/entry_points.txt
lamar-1.0.4.dist-info/top_level.txt
lamar-1.0.4.dist-info/RECORD
